{
    "name": "ShowJointTypes",
    "nickname": "ShowJointTypes",
    "category": "COMPAS Timber",
    "subcategory": "Show",
    "description": "Show the names of the defined Joints",
    "exposure": 4,
    "ghpython": {
        "isAdvancedMode": true,
        "iconDisplay": 0,
        "inputParameters": [
             
            {
                "name": "JointsCollection",
                "description": "A Collection of parts, e.g. JointDefinitions.",
                "typeHintID": "none",
                "scriptParamAccess": 0
            }
        ],
        "outputParameters": [
        ]
    }
}
